{
  "imageWidth": 1280,
  "imageHeight": 720,
  "shapes": [
    {
      "label": "billboard",
      "shape_type": "polygon",
      "points": [
        [
          359.0,
          49.0
        ],
        [
          355.0,
          46.0
        ],
        [
          122.0,
          48.0
        ],
        [
          131.0,
          76.0
        ],
        [
          141.0,
          89.0
        ],
        [
          149.0,
          92.0
        ],
        [
          257.0,
          90.0
        ],
        [
          267.0,
          76.0
        ],
        [
          286.0,
          70.0
        ],
        [
          343.0,
          70.0
        ],
        [
          352.0,
          62.0
        ]
      ]
    }
  ],
  "frameLabel": "billboard"
}