{
  "imageWidth": 1280,
  "imageHeight": 720,
  "shapes": [
    {
      "label": "billboard",
      "shape_type": "polygon",
      "points": [
        [
          431.0,
          374.0
        ],
        [
          432.0,
          543.0
        ],
        [
          438.0,
          551.0
        ],
        [
          434.0,
          555.0
        ],
        [
          439.0,
          561.0
        ],
        [
          537.0,
          571.0
        ],
        [
          551.0,
          580.0
        ],
        [
          730.0,
          589.0
        ],
        [
          732.0,
          593.0
        ],
        [
          765.0,
          596.0
        ],
        [
          797.0,
          595.0
        ],
        [
          800.0,
          583.0
        ],
        [
          815.0,
          576.0
        ],
        [
          817.0,
          572.0
        ],
        [
          816.0,
          540.0
        ],
        [
          798.0,
          513.0
        ],
        [
          798.0,
          470.0
        ],
        [
          788.0,
          430.0
        ],
        [
          783.0,
          424.0
        ],
        [
          785.0,
          408.0
        ],
        [
          762.0,
          404.0
        ],
        [
          755.0,
          415.0
        ],
        [
          742.0,
          422.0
        ],
        [
          717.0,
          408.0
        ],
        [
          716.0,
          393.0
        ],
        [
          702.0,
          390.0
        ]
      ]
    },
    {
      "label": "billboard",
      "shape_type": "polygon",
      "points": [
        [
          879.0,
          428.0
        ],
        [
          877.0,
          438.0
        ],
        [
          873.0,
          440.0
        ],
        [
          877.0,
          445.0
        ],
        [
          870.0,
          454.0
        ],
        [
          880.0,
          479.0
        ],
        [
          882.0,
          560.0
        ],
        [
          891.0,
          565.0
        ],
        [
          897.0,
          573.0
        ],
        [
          900.0,
          586.0
        ],
        [
          901.0,
          606.0
        ],
        [
          917.0,
          606.0
        ],
        [
          924.0,
          613.0
        ],
        [
          939.0,
          616.0
        ],
        [
          1026.0,
          618.0
        ],
        [
          1041.0,
          628.0
        ],
        [
          1072.0,
          627.0
        ],
        [
          1081.0,
          617.0
        ],
        [
          1096.0,
          616.0
        ],
        [
          1100.0,
          608.0
        ],
        [
          1113.0,
          607.0
        ],
        [
          1118.0,
          610.0
        ],
        [
          1120.0,
          617.0
        ],
        [
          1151.0,
          616.0
        ],
        [
          1160.0,
          624.0
        ],
        [
          1161.0,
          640.0
        ],
        [
          1236.0,
          647.0
        ],
        [
          1240.0,
          640.0
        ],
        [
          1256.0,
          636.0
        ],
        [
          1258.0,
          563.0
        ],
        [
          1250.0,
          557.0
        ],
        [
          1255.0,
          552.0
        ],
        [
          1239.0,
          548.0
        ],
        [
          1239.0,
          524.0
        ],
        [
          1213.0,
          517.0
        ],
        [
          1209.0,
          514.0
        ],
        [
          1199.0,
          497.0
        ],
        [
          1199.0,
          487.0
        ],
        [
          1207.0,
          480.0
        ],
        [
          1209.0,
          473.0
        ],
        [
          1218.0,
          468.0
        ],
        [
          1222.0,
          460.0
        ],
        [
          1269.0,
          459.0
        ],
        [
          1270.0,
          451.0
        ],
        [
          1136.0,
          435.0
        ],
        [
          922.0,
          417.0
        ],
        [
          890.0,
          419.0
        ]
      ]
    },
    {
      "label": "billboard",
      "shape_type": "polygon",
      "points": [
        [
          201.0,
          372.0
        ],
        [
          201.0,
          380.0
        ],
        [
          205.0,
          383.0
        ],
        [
          201.0,
          393.0
        ],
        [
          202.0,
          542.0
        ],
        [
          229.0,
          550.0
        ],
        [
          310.0,
          554.0
        ],
        [
          327.0,
          550.0
        ],
        [
          331.0,
          554.0
        ],
        [
          369.0,
          554.0
        ],
        [
          406.0,
          560.0
        ],
        [
          409.0,
          557.0
        ],
        [
          414.0,
          539.0
        ],
        [
          414.0,
          474.0
        ],
        [
          412.0,
          380.0
        ],
        [
          407.0,
          371.0
        ],
        [
          234.0,
          364.0
        ],
        [
          210.0,
          366.0
        ]
      ]
    },
    {
      "label": "billboard",
      "shape_type": "polygon",
      "points": [
        [
          158.0,
          366.0
        ],
        [
          144.0,
          363.0
        ],
        [
          28.0,
          372.0
        ],
        [
          21.0,
          373.0
        ],
        [
          12.0,
          377.0
        ],
        [
          7.0,
          400.0
        ],
        [
          5.0,
          403.0
        ],
        [
          0.0,
          405.0
        ],
        [
          0.0,
          522.0
        ],
        [
          7.0,
          538.0
        ],
        [
          6.0,
          555.0
        ],
        [
          12.0,
          564.0
        ],
        [
          167.0,
          544.0
        ],
        [
          178.0,
          538.0
        ],
        [
          168.0,
          509.0
        ],
        [
          167.0,
          417.0
        ],
        [
          159.0,
          392.0
        ]
      ]
    }
  ],
  "frameLabel": "billboard"
}